[
  {
    "id": "0ss54das5da5sd14a15da5sd4asf5d4gqw",
    "title": "Staffing Plan 01/10/25",
    "isEditMode": false,
    "chatbotInput": "",
    "selectedProjects": [],
    "chat": []
  },
  {
    "id": "0ss54das5da5sd14a15da5sd4asf5d4gqw2",
    "title": "Staffing Plan 01/10/25",
    "isEditMode": false,
    "chatbotInput": "",
    "selectedProjects": [],
    "chat": []
  },
  {
    "id": "0ss54das5da5sd14a15da5sd4asf5d4gqw3",
    "title": "Staffing Plan 01/10/25",
    "isEditMode": false,
    "chatbotInput": "",
    "selectedProjects": [],
    "chat": []
  },
  {
    "id": "0ss54das5da5sd14a15da5sd4asf5d4gqw4",
    "title": "Staffing Plan 01/10/25",
    "isEditMode": false,
    "chatbotInput": "",
    "selectedProjects": [],
    "chat": []
  },
  {
    "id": "0ss54das5da5sd14a15da5sd4asf5d4gqw5",
    "title": "Example",
    "isEditMode": false,
    "selectedProjects": [],
    "chatbotInput": "",
    "chat": [
      {
        "id": 1,
        "sender": "user",
        "message": ["Hi there! Give me the staffing plan fot he selected projects"],
        "timestamp": "2025-03-10T10:00:00Z"
      },
      {
        "id": 2,
        "sender": "ai",
        "message": ["Here is you requested Staffing Plan"],
        "timestamp": "2025-03-10T10:00:02Z"
      },
      {
        "id": 3,
        "sender": "user",
        "message": ["Remove Frank Gavin and George Neha from the case and update the end date to January 31, 2025"],
        "timestamp": "2025-03-10T10:01:00Z"
      }, {

        "id": 4,
        "sender": "ai",
        "message": ["Answer example"],
        "timestamp": "2025-03-10T10:01:00Z"
      }, {

        "id": 5,
        "sender": "ai",
        "table": true,
        "resources": {
          "resources": [
            {
              "id": 1,
              "name": "Hillman Corp",
              "code": "010",
              "type": "project",
              "bookingType": "(Sydney)(Team: 4 | Prio: 1 | Lang: English, French)(Start date: Oct 02, 2025 | End date: Dec 31, 2025)",
              "office": "SYD",
              "startWeek": 1,
              "filledColor": "#8367E7",
              "length": 12
            },
            {
              "id": 2,
              "name": "Taza, Cam",
              "deleted":true,
              "code": "001",
              "type": "AC",
              "alertMessage": "Vacation from  07-dec-2025 til 11-dec-2025. In x day(s)",
              "office": "SYD",
              "startWeek": 2,
              "filledColor": "#F6F1FE",
              "length": 12
            },
            {
              "id": 3,
              "name": "Johnson, Mitchell",
              "code": "012",
              "deleted": true,
              "type": "C",
              "office": "SYD",
              "startWeek": 1,
              "filledColor": "#F6F1FE",
              "length": 12
            },
            {
              "id": 4,
              "name": "Markle, Elizabeth",
              "code": "015",
              "type": "C",
              "office": "SYD",
              "startWeek": 1,
              "filledColor": "#F6F1FE",
              "length": 12
            },
            {
              "id": 5,
              "name": "Epiar, Rohan",
              "code": "017",
              "type": "M",
              "office": "SYD",
              "startWeek": 1,
              "filledColor": "#F6F1FE",
              "length": 12
            },
            {
              "id": 6,
              "name": "Intercontinental",
              "code": "016",
              "type": "project",
              "bookingType": "(Sydney)(Team: 4 | Prio: 1 | Lang: Spanish)(Start date: Oct 02, 2025 | End date: Dec 31, 2025)",
              "office": "SYD",
              "startWeek": 3,
              "filledColor": "#8EB97A",
              "length": 12
            },
            {
              "id": 7,
              "name": "Jones, Madison",
              "code": "105",
              "type": "AC",
              "office": "SYD",
              "startWeek": 3,
              "filledColor": "#ECF3E8",
              "length": 12
            },
            {
              "id": 8,
              "name": "Ozyamp, Clara",
              "code": "090",
              "type": "C",
              "office": "SYD",
              "startWeek": 3,
              "filledColor": "#ECF3E8",
              "length": 12
            },
            {
              "id": 9,
              "name": "Roos, Ethan",
              "code": "012",
              "type": "C",
              "office": "BOS",
              "startWeek": 3,
              "filledColor": "#ECF3E8",
              "length": 12
            },
            {
              "id": 10,
              "name": "Haste, Clayton",
              "code": "017",
              "type": "M",
              "office": "CIS",
              "startWeek": 3,
              "filledColor": "#ECF3E8",
              "length": 12
            },
            {
              "id": 11,
              "name": "R&D Design",
              "code": "017",
              "type": "project",
              "bookingType": "(Sydney)(Team: 4 | Prio: 1 | Lang: English)(Start date: Oct 02, 2025 | End date: Dec 31, 2025)",
              "office": "SYD",
              "startWeek": 1,
              "filledColor": "#F95B3F",
              "length": 12
            },
            {
              "id": 12,
              "name": "Gavin, Frank",
              "alertMessage": "Vacation from  07-dec-2025 til 11-dec-2025. In x day(s)",
              "code": "070",
              "type": "AC",
              "office": "SYD",
              "startWeek": 1,
              "filledColor": "#FDEABA",
              "deleted": null,
              "length": 12
            },
            {
              "id": 13,
              "name": "Nellia, George",
              "deleted": null,
              "code": "010",
              "type": "C",
              "office": "CIS",
              "startWeek": 1,
              "filledColor": "#FDEABA",
              "length": 12
            },
            {
              "id": 14,
              "name": "Lewis, Melton",
              "code": "025",
              "type": "C",
              "office": "SYD",
              "startWeek": 1,
              "filledColor": "#FDEABA",
              "length": 12
            },
            {
              "id": 15,
              "name": "Whiteside, Anna",
              "code": "016",
              "type": "M",
              "office": "SYD",
              "startWeek": 1,
              "filledColor": "#FDEABA",
              "length": 12
            }
          ],
          "feedback": "",
          "showChanges": false
        },

        "timestamp": "2025-03-10T10:01:00Z"
      }
    ]
  }
]
